CHANGES.rst
MANIFEST.in
README.rst
animation.gif
setup.cfg
setup.py
SudokuStudyLib.egg-info/PKG-INFO
SudokuStudyLib.egg-info/SOURCES.txt
SudokuStudyLib.egg-info/dependency_links.txt
SudokuStudyLib.egg-info/not-zip-safe
SudokuStudyLib.egg-info/top_level.txt
docs/make.bat
docs/build/doctrees/base.doctree
docs/build/doctrees/courses.doctree
docs/build/doctrees/data.doctree
docs/build/doctrees/environment.pickle
docs/build/doctrees/index.doctree
docs/build/doctrees/intro.doctree
docs/build/doctrees/logic.doctree
docs/build/doctrees/program.doctree
docs/build/doctrees/sudoku.doctree
docs/build/html/.buildinfo
docs/build/html/base.html
docs/build/html/courses.html
docs/build/html/data.html
docs/build/html/genindex.html
docs/build/html/index.html
docs/build/html/intro.html
docs/build/html/logic.html
docs/build/html/objects.inv
docs/build/html/program.html
docs/build/html/py-modindex.html
docs/build/html/search.html
docs/build/html/searchindex.js
docs/build/html/sudoku.html
docs/build/html/_images/flowchart.png
docs/build/html/_images/m3.png
docs/build/html/_images/origin.png
docs/build/html/_images/p1.png
docs/build/html/_images/p2.png
docs/build/html/_images/p3.png
docs/build/html/_images/p4.png
docs/build/html/_images/p5.png
docs/build/html/_images/p6.png
docs/build/html/_images/p7.png
docs/build/html/_images/result.png
docs/build/html/_modules/index.html
docs/build/html/_modules/sudoku/sudoku.html
docs/build/html/_sources/base.txt
docs/build/html/_sources/courses.txt
docs/build/html/_sources/data.txt
docs/build/html/_sources/index.txt
docs/build/html/_sources/intro.txt
docs/build/html/_sources/logic.txt
docs/build/html/_sources/program.txt
docs/build/html/_sources/sudoku.txt
docs/build/html/_static/ajax-loader.gif
docs/build/html/_static/basic.css
docs/build/html/_static/comment-bright.png
docs/build/html/_static/comment-close.png
docs/build/html/_static/comment.png
docs/build/html/_static/default.css
docs/build/html/_static/doctools.js
docs/build/html/_static/down-pressed.png
docs/build/html/_static/down.png
docs/build/html/_static/file.png
docs/build/html/_static/jquery.js
docs/build/html/_static/minus.png
docs/build/html/_static/plus.png
