Metadata-Version: 1.1
Name: SudokuStudyLib
Version: 1.0.7
Summary: Sudoku Solving Library
Home-page: https://github.com/RobertOfTaiwan/SudokuStudyLib
Author: Robert J. Hwang
Author-email: RobertOfTaiwan@gmail.com
License: MIT
Keywords: sudoku,python,studying
Platform: UNKNOWN
Classifier: Operating System :: OS Independent
Classifier: Environment :: Console
Classifier: Programming Language :: Python :: 3
Classifier: Topic :: Games/Entertainment :: Puzzle Games
Classifier: Topic :: Education
Classifier: Topic :: Scientific/Engineering :: Mathematics
Classifier: Intended Audience :: Developers
Classifier: Intended Audience :: Education
Classifier: Intended Audience :: End Users/Desktop
Classifier: Natural Language :: English
Classifier: Natural Language :: Chinese (Traditional)
